thumbor_cassandra/__init__.py
thumbor_cassandra/_version.py
thumbor_cassandra/loader.py
thumbor_cassandra-1.0.dist-info/LICENSE
thumbor_cassandra-1.0.dist-info/METADATA
thumbor_cassandra-1.0.dist-info/WHEEL
thumbor_cassandra-1.0.dist-info/top_level.txt
thumbor_cassandra-1.0.dist-info/RECORD
