Metadata-Version: 2.1
Name: thumbor-cassandra
Version: 1.0
Summary: Apache Cassandra loader for Thumbor
Home-page: https://github.com/glborges/thumbor-cassandra
Author: Guilherme Borges
Author-email: illidam.lopes@gmail.com
License: MIT
Keywords: thumbor,cassandra,images
Platform: UNKNOWN
Classifier: Intended Audience :: Developers
Classifier: License :: OSI Approved :: MIT License
Classifier: Natural Language :: Portuguese
Classifier: Programming Language :: Python :: 2.7
Classifier: Topic :: Internet :: WWW/HTTP :: Dynamic Content
Classifier: Topic :: Multimedia :: Graphics :: Presentation
Requires-Dist: thumbor
Requires-Dist: cassandra-driver
